{
  "version": "2.4.4",
  "flags": {},
  "shapes": [
    {
      "label": "IronChunk",
      "score": null,
      "points": [
        [
          2.9824561403509584,
          562.3684210526316
        ],
        [
          549.0,
          562.3684210526316
        ],
        [
          549.0,
          1079
        ],
        [
          2.9824561403509584,
          1079
        ]
      ],
      "group_id": null,
      "description": "",
      "difficult": false,
      "shape_type": "rectangle",
      "flags": {},
      "attributes": {},
      "kie_linking": []
    }
  ],
  "imagePath": "..\\images\\CondessenceCrystalNatlanHD 0148.jpg",
  "imageData": null,
  "imageHeight": 1080,
  "imageWidth": 1920
}